hyperbolicMDS/__init__.py
hyperbolicMDS/_version.py
hyperbolicMDS/mds.py
hyperbolicMDS-0.1.10.dist-info/METADATA
hyperbolicMDS-0.1.10.dist-info/WHEEL
hyperbolicMDS-0.1.10.dist-info/top_level.txt
hyperbolicMDS-0.1.10.dist-info/RECORD
