Metadata-Version: 2.1
Name: hyperbolicMDS
Version: 0.1.10
Summary: hyperbolic mds in the poincare ball
Home-page: https://github.com/enlberman/hyperbolicMDS
Author: Andrew J. Stier
Author-email: andrewstier@uchicago.edu
Maintainer: Andrew J. Stier
Maintainer-email: andrewstier@uchicago.edu
License: MIT
Platform: OS Independent
Classifier: Environment :: Console
Classifier: Intended Audience :: Science/Research
Classifier: License :: OSI Approved :: MIT License
Classifier: Operating System :: OS Independent
Classifier: Programming Language :: Python
Classifier: Topic :: Scientific/Engineering
Requires-Dist: numpy
Requires-Dist: packaging
Requires-Dist: scipy
Requires-Dist: pathlib
Requires-Dist: argparse
Requires-Dist: datetime
